{
	"alias": "FEDORA-EPEL-2022-5d0edca089",
	"autokarma": true,
	"autotime": true,
	"bugs": [
		{
			"bug_id": 2063567,
			"title": "libopenmpt-0.6.3 is available",
			"bugzilla": {
				"bug_id": "2063567",
				"creation_ts": "2022-03-13 18:45:34 +0000",
				"short_desc": "libopenmpt-0.6.3 is available",
				"delta_ts": "2022-05-11 02:03:27 +0000",
				"bug_status": "CLOSED",
				"resolution": "ERRATA",
				"keywords": "FutureFeature, Triaged",
				"priority": "unspecified",
				"bug_severity": "unspecified",
				"long_desc": [
					{
						"isprivate": "0",
						"commentid": "16042396",
						"comment_count": "0",
						"who": {
							"text": "upstream-release-monitoring",
							"name": "Upstream Release Monitoring"
						},
						"bug_when": "2022-03-13 18:45:34 +0000",
						"thetext": "Latest upstream release: 0.6.2\nCurrent version/release in rawhide: 0.6.1-1.fc37\nURL: https://lib.openmpt.org/libopenmpt/\n\nPlease consult the package updates policy before you issue an update to a stable branch: https://docs.fedoraproject.org/en-US/fesco/Updates_Policy/\n\n\nMore information about the service that created this bug can be found at: https://fedoraproject.org/wiki/Upstream_release_monitoring\n\n\nPlease keep in mind that with any upstream change, there may also be packaging changes that need to be made. Specifically, please remember that it is your responsibility to review the new version to ensure that the licensing is still correct and that no non-free or legally problematic items have been added upstream.\n\n\nBased on the information from Anitya: https://release-monitoring.org/project/141468/"
					},
					{
						"isprivate": "0",
						"commentid": "16169237",
						"comment_count": "1",
						"who": {
							"text": "upstream-release-monitoring",
							"name": "Upstream Release Monitoring"
						},
						"bug_when": "2022-04-24 17:41:10 +0000",
						"thetext": "Latest upstream release: 0.6.3\nCurrent version/release in rawhide: 0.6.1-1.fc37\nURL: https://lib.openmpt.org/libopenmpt/\n\nPlease consult the package updates policy before you issue an update to a stable branch: https://docs.fedoraproject.org/en-US/fesco/Updates_Policy/\n\n\nMore information about the service that created this bug can be found at: https://fedoraproject.org/wiki/Upstream_release_monitoring\n\n\nPlease keep in mind that with any upstream change, there may also be packaging changes that need to be made. Specifically, please remember that it is your responsibility to review the new version to ensure that the licensing is still correct and that no non-free or legally problematic items have been added upstream.\n\n\nBased on the information from Anitya: https://release-monitoring.org/project/141468/"
					},
					{
						"isprivate": "0",
						"commentid": "16194594",
						"comment_count": "2",
						"who": {
							"text": "updates",
							"name": "Fedora Update System"
						},
						"bug_when": "2022-05-02 21:50:58 +0000",
						"thetext": "FEDORA-EPEL-2022-1709e5c07f has been submitted as an update to Fedora EPEL 8. https://bodhi.fedoraproject.org/updates/FEDORA-EPEL-2022-1709e5c07f"
					},
					{
						"isprivate": "0",
						"commentid": "16194595",
						"comment_count": "3",
						"who": {
							"text": "updates",
							"name": "Fedora Update System"
						},
						"bug_when": "2022-05-02 21:50:59 +0000",
						"thetext": "FEDORA-EPEL-2022-5d0edca089 has been submitted as an update to Fedora EPEL 9. https://bodhi.fedoraproject.org/updates/FEDORA-EPEL-2022-5d0edca089"
					},
					{
						"isprivate": "0",
						"commentid": "16194596",
						"comment_count": "4",
						"who": {
							"text": "updates",
							"name": "Fedora Update System"
						},
						"bug_when": "2022-05-02 21:51:00 +0000",
						"thetext": "FEDORA-EPEL-2022-4b9c772ddc has been submitted as an update to Fedora EPEL 7. https://bodhi.fedoraproject.org/updates/FEDORA-EPEL-2022-4b9c772ddc"
					},
					{
						"isprivate": "0",
						"commentid": "16196769",
						"comment_count": "5",
						"who": {
							"text": "updates",
							"name": "Fedora Update System"
						},
						"bug_when": "2022-05-03 15:24:48 +0000",
						"thetext": "FEDORA-EPEL-2022-4b9c772ddc has been pushed to the Fedora EPEL 7 testing repository.\n\nYou can provide feedback for this update here: https://bodhi.fedoraproject.org/updates/FEDORA-EPEL-2022-4b9c772ddc\n\nSee also https://fedoraproject.org/wiki/QA:Updates_Testing for more information on how to test updates."
					},
					{
						"isprivate": "0",
						"commentid": "16196776",
						"comment_count": "6",
						"who": {
							"text": "updates",
							"name": "Fedora Update System"
						},
						"bug_when": "2022-05-03 15:25:20 +0000",
						"thetext": "FEDORA-EPEL-2022-5d0edca089 has been pushed to the Fedora EPEL 9 testing repository.\n\nYou can provide feedback for this update here: https://bodhi.fedoraproject.org/updates/FEDORA-EPEL-2022-5d0edca089\n\nSee also https://fedoraproject.org/wiki/QA:Updates_Testing for more information on how to test updates."
					},
					{
						"isprivate": "0",
						"commentid": "16196855",
						"comment_count": "7",
						"who": {
							"text": "updates",
							"name": "Fedora Update System"
						},
						"bug_when": "2022-05-03 15:44:09 +0000",
						"thetext": "FEDORA-EPEL-2022-1709e5c07f has been pushed to the Fedora EPEL 8 testing repository.\n\nYou can provide feedback for this update here: https://bodhi.fedoraproject.org/updates/FEDORA-EPEL-2022-1709e5c07f\n\nSee also https://fedoraproject.org/wiki/QA:Updates_Testing for more information on how to test updates."
					},
					{
						"isprivate": "0",
						"commentid": "16227182",
						"comment_count": "8",
						"who": {
							"text": "updates",
							"name": "Fedora Update System"
						},
						"bug_when": "2022-05-11 01:40:47 +0000",
						"thetext": "FEDORA-EPEL-2022-1709e5c07f has been pushed to the Fedora EPEL 8 stable repository.\nIf problem still persists, please make note of it in this bug report."
					},
					{
						"isprivate": "0",
						"commentid": "16227191",
						"comment_count": "9",
						"who": {
							"text": "updates",
							"name": "Fedora Update System"
						},
						"bug_when": "2022-05-11 01:41:44 +0000",
						"thetext": "FEDORA-EPEL-2022-5d0edca089 has been pushed to the Fedora EPEL 9 stable repository.\nIf problem still persists, please make note of it in this bug report."
					},
					{
						"isprivate": "0",
						"commentid": "16227214",
						"comment_count": "10",
						"who": {
							"text": "updates",
							"name": "Fedora Update System"
						},
						"bug_when": "2022-05-11 02:03:27 +0000",
						"thetext": "FEDORA-EPEL-2022-4b9c772ddc has been pushed to the Fedora EPEL 7 stable repository.\nIf problem still persists, please make note of it in this bug report."
					}
				]
			}
		}
	],
	"builds": [
		{
			"epoch": 0,
			"nvr": "libopenmpt-0.6.3-1.el9",
			"release_id": 61,
			"signed": true,
			"type": "rpm",
			"package": {
				"aarch64": [
					{
						"name": "libopenmpt-debuginfo",
						"version": "0.6.3",
						"release": "1.el9",
						"arch": "aarch64"
					},
					{
						"name": "libopenmpt-devel",
						"version": "0.6.3",
						"release": "1.el9",
						"arch": "aarch64"
					},
					{
						"name": "openmpt123-debuginfo",
						"version": "0.6.3",
						"release": "1.el9",
						"arch": "aarch64"
					},
					{
						"name": "libopenmpt",
						"version": "0.6.3",
						"release": "1.el9",
						"arch": "aarch64"
					},
					{
						"name": "libopenmpt-debugsource",
						"version": "0.6.3",
						"release": "1.el9",
						"arch": "aarch64"
					},
					{
						"name": "openmpt123",
						"version": "0.6.3",
						"release": "1.el9",
						"arch": "aarch64"
					}
				],
				"ppc64le": [
					{
						"name": "libopenmpt-debuginfo",
						"version": "0.6.3",
						"release": "1.el9",
						"arch": "ppc64le"
					},
					{
						"name": "openmpt123-debuginfo",
						"version": "0.6.3",
						"release": "1.el9",
						"arch": "ppc64le"
					},
					{
						"name": "libopenmpt-devel",
						"version": "0.6.3",
						"release": "1.el9",
						"arch": "ppc64le"
					},
					{
						"name": "openmpt123",
						"version": "0.6.3",
						"release": "1.el9",
						"arch": "ppc64le"
					},
					{
						"name": "libopenmpt",
						"version": "0.6.3",
						"release": "1.el9",
						"arch": "ppc64le"
					},
					{
						"name": "libopenmpt-debugsource",
						"version": "0.6.3",
						"release": "1.el9",
						"arch": "ppc64le"
					}
				],
				"s390x": [
					{
						"name": "libopenmpt-debuginfo",
						"version": "0.6.3",
						"release": "1.el9",
						"arch": "s390x"
					},
					{
						"name": "libopenmpt-debugsource",
						"version": "0.6.3",
						"release": "1.el9",
						"arch": "s390x"
					},
					{
						"name": "openmpt123-debuginfo",
						"version": "0.6.3",
						"release": "1.el9",
						"arch": "s390x"
					},
					{
						"name": "libopenmpt",
						"version": "0.6.3",
						"release": "1.el9",
						"arch": "s390x"
					},
					{
						"name": "libopenmpt-devel",
						"version": "0.6.3",
						"release": "1.el9",
						"arch": "s390x"
					},
					{
						"name": "openmpt123",
						"version": "0.6.3",
						"release": "1.el9",
						"arch": "s390x"
					}
				],
				"src": [
					{
						"name": "libopenmpt",
						"version": "0.6.3",
						"release": "1.el9",
						"arch": "src"
					}
				],
				"x86_64": [
					{
						"name": "libopenmpt-debuginfo",
						"version": "0.6.3",
						"release": "1.el9",
						"arch": "x86_64"
					},
					{
						"name": "openmpt123-debuginfo",
						"version": "0.6.3",
						"release": "1.el9",
						"arch": "x86_64"
					},
					{
						"name": "libopenmpt-devel",
						"version": "0.6.3",
						"release": "1.el9",
						"arch": "x86_64"
					},
					{
						"name": "libopenmpt",
						"version": "0.6.3",
						"release": "1.el9",
						"arch": "x86_64"
					},
					{
						"name": "openmpt123",
						"version": "0.6.3",
						"release": "1.el9",
						"arch": "x86_64"
					},
					{
						"name": "libopenmpt-debugsource",
						"version": "0.6.3",
						"release": "1.el9",
						"arch": "x86_64"
					}
				]
			}
		}
	],
	"close_bugs": true,
	"comments": [
		{
			"id": 2513657,
			"text": "This update has been submitted for testing by robert. ",
			"timestamp": "2022-05-02 21:50:56",
			"update_id": 402497,
			"user": {
				"avatar": "https://apps.fedoraproject.org/img/icons/bodhi-24.png",
				"id": 91,
				"name": "bodhi",
				"openid": "bodhi.id.fedoraproject.org"
			},
			"user_id": 91
		},
		{
			"id": 2513658,
			"text": "This update's test gating status has been changed to 'ignored'.",
			"timestamp": "2022-05-02 21:50:57",
			"update_id": 402497,
			"user": {
				"avatar": "https://apps.fedoraproject.org/img/icons/bodhi-24.png",
				"id": 91,
				"name": "bodhi",
				"openid": "bodhi.id.fedoraproject.org"
			},
			"user_id": 91
		},
		{
			"id": 2514495,
			"text": "This update has been pushed to testing.",
			"timestamp": "2022-05-03 15:25:24",
			"update_id": 402497,
			"user": {
				"avatar": "https://apps.fedoraproject.org/img/icons/bodhi-24.png",
				"id": 91,
				"name": "bodhi",
				"openid": "bodhi.id.fedoraproject.org"
			},
			"user_id": 91
		},
		{
			"id": 2522906,
			"text": "This update has been submitted for stable by bodhi. ",
			"timestamp": "2022-05-10 15:25:27",
			"update_id": 402497,
			"user": {
				"avatar": "https://apps.fedoraproject.org/img/icons/bodhi-24.png",
				"id": 91,
				"name": "bodhi",
				"openid": "bodhi.id.fedoraproject.org"
			},
			"user_id": 91
		},
		{
			"id": 2523427,
			"text": "This update has been pushed to stable.",
			"timestamp": "2022-05-11 01:41:46",
			"update_id": 402497,
			"user": {
				"avatar": "https://apps.fedoraproject.org/img/icons/bodhi-24.png",
				"id": 91,
				"name": "bodhi",
				"openid": "bodhi.id.fedoraproject.org"
			},
			"user_id": 91
		}
	],
	"content_type": "rpm",
	"date_pushed": "2022-05-11 01:41:36",
	"date_stable": "2022-05-11 01:41:36",
	"date_submitted": "2022-05-02 21:50:56",
	"date_testing": "2022-05-03 15:25:13",
	"meets_testing_requirements": true,
	"notes": "# libopenmpt 0.6.3 (2022-04-24)\n\n  * Pitch / Pan Separation and Random Variation instrument properties were not resetting properly when seeking, potentially causing instruments to be played e.g. at a vastly different pan position compared to playing the module continuously.\n  * MED: Stereo samples were not imported correctly.\n  * zlib: Update to v1.2.12 (2022-03-27).\n\n# libopenmpt 0.6.2 (2022-03-13)\n  * [Sec] Possible out-of-bounds write in malformed IT / XM / MPTM files using the internal LFO plugin. (r17076)\n  * [Sec] Possible out-of-bounds read when using Amiga BLEP interpolation with extremely high-pitched notes. (r17078, r17079)\n  * ISO-8859-1-related charsets from Amiga OS and RISC OS are now handled more accurately, thus avoiding some unwanted control characters.\n  * MO3: Pattern indices 254 / 255 were not treated as playable patterns even if the original file was a MOD / XM.\n  * Correctly apply ST3-style effect memory when seeking in S3M files.\n  * Command S (S3M / IT style) effect memory was not applied when seeking.\n  * Initial channel mute status was not reported correctly in `get_channel_mute_status` since libopenmpt 0.6.0.\n  * FLAC: Update to v1.3.4 (2022-02-21).\n  * pugixml: Update to v1.12.1 (2022-02-16).",
	"pushed": true,
	"release": {
		"branch": "epel9",
		"candidate_tag": "epel9-testing-candidate",
		"composed_by_bodhi": true,
		"create_automatic_updates": false,
		"dist_tag": "epel9",
		"id_prefix": "FEDORA-EPEL",
		"long_name": "Fedora EPEL 9",
		"mail_template": "fedora_epel_legacy_errata_template",
		"name": "EPEL-9",
		"override_tag": "epel9-override",
		"package_manager": "unspecified",
		"pending_signing_tag": "epel9-signing-pending",
		"pending_stable_tag": "epel9-pending",
		"pending_testing_tag": "epel9-testing-pending",
		"stable_tag": "epel9",
		"state": "current",
		"testing_tag": "epel9-testing",
		"version": "9"
	},
	"require_bugs": true,
	"require_testcases": true,
	"severity": "medium",
	"stable_days": 7,
	"stable_karma": 3,
	"status": "stable",
	"suggest": "unspecified",
	"test_gating_status": "ignored",
	"title": "libopenmpt-0.6.3-1.el9",
	"type": "security",
	"url": "https://bodhi.fedoraproject.org/updates/FEDORA-EPEL-2022-5d0edca089",
	"unstable_karma": -3,
	"updateid": "FEDORA-EPEL-2022-5d0edca089",
	"user": {
		"avatar": "https://seccdn.libravatar.org/avatar/74d863c618d1ff08d6ed19e90c58349761e8a5fa7888ce464063fc2809ba7dc2?s=24&d=retro",
		"email": "redhat@linuxnetz.de",
		"groups": [
			{
				"name": "proventesters"
			},
			{
				"name": "provenpackager"
			},
			{
				"name": "packager"
			},
			{
				"name": "ipausers"
			},
			{
				"name": "ambassadors"
			},
			{
				"name": "campusambassadors"
			},
			{
				"name": "gitfedora-web"
			},
			{
				"name": "fedora-contributor"
			},
			{
				"name": "advocates"
			},
			{
				"name": "fedorabugs"
			},
			{
				"name": "gitsecurity-spin"
			},
			{
				"name": "signed_fpca"
			},
			{
				"name": "gitfama"
			},
			{
				"name": "epel-packagers-sig"
			},
			{
				"name": "web"
			},
			{
				"name": "clamav"
			},
			{
				"name": "trust admins"
			}
		],
		"id": 172,
		"name": "robert",
		"openid": "robert.id.fedoraproject.org"
	},
	"version_hash": "df71793373e09edb8023131c29c1dc55238e125d"
}
