{
	"alias": "FEDORA-2022-95000d85e2",
	"autokarma": true,
	"autotime": true,
	"bugs": [
		{
			"bug_id": 2130202,
			"security": true,
			"title": "libofx: memory issues in libofx [fedora-all]",
			"bugzilla": {
				"bug_id": "2130202",
				"creation_ts": "2022-09-27 13:36:02 +0000",
				"short_desc": "libofx: memory issues in libofx [fedora-all]",
				"delta_ts": "2022-09-29 02:20:37 +0000",
				"bug_status": "CLOSED",
				"resolution": "ERRATA",
				"keywords": "Security, SecurityTracking",
				"priority": "medium",
				"bug_severity": "medium",
				"blocked": [
					{
						"bug_id": "2130201",
						"creation_ts": "2022-09-27 13:35:44 +0000",
						"short_desc": "libofx: memory issues in libofx",
						"delta_ts": "2022-11-28 12:26:44 +0000",
						"bug_status": "CLOSED",
						"resolution": "UPSTREAM",
						"keywords": "Security",
						"priority": "medium",
						"bug_severity": "medium",
						"depends_on": [
							"2130203",
							"2130202"
						],
						"long_desc": [
							{
								"isprivate": "0",
								"commentid": "16669081",
								"comment_count": "0",
								"who": {
									"text": "trathi",
									"name": "TEJ RATHI"
								},
								"bug_when": "2022-09-27 13:35:44 +0000",
								"thetext": "Various memory related issues found in libofx library\n\nhttps://github.com/libofx/libofx/issues/86\nhttps://bugzilla.redhat.com/show_bug.cgi?id=2127755"
							},
							{
								"isprivate": "0",
								"commentid": "16669088",
								"comment_count": "1",
								"who": {
									"text": "trathi",
									"name": "TEJ RATHI"
								},
								"bug_when": "2022-09-27 13:36:20 +0000",
								"thetext": "Created libofx tracking bugs for this issue:\n\nAffects: epel-all [bug 2130203]\nAffects: fedora-all [bug 2130202]"
							},
							{
								"isprivate": "0",
								"commentid": "16825660",
								"comment_count": "2",
								"who": {
									"text": "prodsec-dev",
									"name": "Product Security DevOps Team"
								},
								"bug_when": "2022-11-28 12:26:43 +0000",
								"thetext": "This CVE Bugzilla entry is for community support informational purposes only as it does not affect a package in a commercially supported Red Hat product. Refer to the dependent bugs for status of those individual community products."
							}
						]
					}
				],
				"long_desc": [
					{
						"isprivate": "0",
						"commentid": "16669082",
						"comment_count": "0",
						"who": {
							"text": "trathi",
							"name": "TEJ RATHI"
						},
						"bug_when": "2022-09-27 13:36:02 +0000",
						"thetext": "\nThis is an automatically created tracking bug!  It was created to ensure\nthat one or more security vulnerabilities are fixed in affected versions\nof fedora-all.\n\nFor comments that are specific to the vulnerability please use bugs filed\nagainst the \"Security Response\" product referenced in the \"Blocks\" field.\n\nFor more information see:\nhttp://fedoraproject.org/wiki/Security/TrackingBugs\n\nWhen submitting as an update, use the fedpkg template provided in the next\ncomment(s).  This will include the bug IDs of this tracking bug as well as\nthe relevant top-level CVE bugs.\n\nPlease also mention the CVE IDs being fixed in the RPM changelog and the\nfedpkg commit message.\n\nNOTE: this issue affects multiple supported versions of Fedora. While only\none tracking bug has been filed, please correct all affected versions at\nthe same time.  If you need to fix the versions independent of each other,\nyou may clone this bug as appropriate."
					},
					{
						"isprivate": "0",
						"commentid": "16669083",
						"comment_count": "1",
						"who": {
							"text": "trathi",
							"name": "TEJ RATHI"
						},
						"bug_when": "2022-09-27 13:36:05 +0000",
						"thetext": "Use the following template to for the 'fedpkg update' request to submit an\nupdate for this issue as it contains the top-level parent bug(s) as well as\nthis tracking bug.  This will ensure that all associated bugs get updated\nwhen new packages are pushed to stable.\n\n=====\n\n# bugfix, security, enhancement, newpackage (required)\ntype=security\n\n# low, medium, high, urgent (required)\nseverity=medium\n\n# testing, stable\nrequest=testing\n\n# Bug numbers: 1234,9876\nbugs=2130201,2130202\n\n# Description of your update\nnotes=Security fix for [PUT CVEs HERE]\n\n# Enable request automation based on the stable/unstable karma thresholds\nautokarma=True\nstable_karma=3\nunstable_karma=-3\n\n# Automatically close bugs when this marked as stable\nclose_bugs=True\n\n# Suggest that users restart after update\nsuggest_reboot=False\n\n======\n\nAdditionally, you may opt to use the bodhi web interface to submit updates:\n\nhttps://bodhi.fedoraproject.org/updates/new"
					},
					{
						"isprivate": "0",
						"commentid": "16669127",
						"comment_count": "2",
						"who": {
							"text": "updates",
							"name": "Fedora Update System"
						},
						"bug_when": "2022-09-27 13:50:53 +0000",
						"thetext": "FEDORA-2022-c9028047bf has been submitted as an update to Fedora 35. https://bodhi.fedoraproject.org/updates/FEDORA-2022-c9028047bf"
					},
					{
						"isprivate": "0",
						"commentid": "16669128",
						"comment_count": "3",
						"who": {
							"text": "updates",
							"name": "Fedora Update System"
						},
						"bug_when": "2022-09-27 13:51:03 +0000",
						"thetext": "FEDORA-2022-95000d85e2 has been submitted as an update to Fedora 36. https://bodhi.fedoraproject.org/updates/FEDORA-2022-95000d85e2"
					},
					{
						"isprivate": "0",
						"commentid": "16669132",
						"comment_count": "4",
						"who": {
							"text": "gwync",
							"name": "Gwyn Ciesla"
						},
						"bug_when": "2022-09-27 13:51:30 +0000",
						"thetext": "*** Bug 2127755 has been marked as a duplicate of this bug. ***"
					},
					{
						"isprivate": "0",
						"commentid": "16671688",
						"comment_count": "5",
						"who": {
							"text": "updates",
							"name": "Fedora Update System"
						},
						"bug_when": "2022-09-28 12:10:44 +0000",
						"thetext": "FEDORA-2022-95000d85e2 has been pushed to the Fedora 36 stable repository.\nIf problem still persists, please make note of it in this bug report."
					},
					{
						"isprivate": "0",
						"commentid": "16673366",
						"comment_count": "6",
						"who": {
							"text": "updates",
							"name": "Fedora Update System"
						},
						"bug_when": "2022-09-29 02:20:37 +0000",
						"thetext": "FEDORA-2022-c9028047bf has been pushed to the Fedora 35 stable repository.\nIf problem still persists, please make note of it in this bug report."
					}
				]
			}
		}
	],
	"builds": [
		{
			"epoch": 0,
			"nvr": "libofx-0.10.7-2.fc36",
			"release_id": 56,
			"signed": true,
			"type": "rpm",
			"package": {
				"aarch64": [
					{
						"name": "ofx-debuginfo",
						"version": "0.10.7",
						"release": "2.fc36",
						"arch": "aarch64"
					},
					{
						"name": "libofx-debugsource",
						"version": "0.10.7",
						"release": "2.fc36",
						"arch": "aarch64"
					},
					{
						"name": "libofx-debuginfo",
						"version": "0.10.7",
						"release": "2.fc36",
						"arch": "aarch64"
					},
					{
						"name": "libofx-devel",
						"version": "0.10.7",
						"release": "2.fc36",
						"arch": "aarch64"
					},
					{
						"name": "libofx",
						"version": "0.10.7",
						"release": "2.fc36",
						"arch": "aarch64"
					},
					{
						"name": "ofx",
						"version": "0.10.7",
						"release": "2.fc36",
						"arch": "aarch64"
					}
				],
				"armv7hl": [
					{
						"name": "ofx-debuginfo",
						"version": "0.10.7",
						"release": "2.fc36",
						"arch": "armv7hl"
					},
					{
						"name": "libofx-debuginfo",
						"version": "0.10.7",
						"release": "2.fc36",
						"arch": "armv7hl"
					},
					{
						"name": "libofx",
						"version": "0.10.7",
						"release": "2.fc36",
						"arch": "armv7hl"
					},
					{
						"name": "libofx-devel",
						"version": "0.10.7",
						"release": "2.fc36",
						"arch": "armv7hl"
					},
					{
						"name": "libofx-debugsource",
						"version": "0.10.7",
						"release": "2.fc36",
						"arch": "armv7hl"
					},
					{
						"name": "ofx",
						"version": "0.10.7",
						"release": "2.fc36",
						"arch": "armv7hl"
					}
				],
				"i686": [
					{
						"name": "libofx-debuginfo",
						"version": "0.10.7",
						"release": "2.fc36",
						"arch": "i686"
					},
					{
						"name": "ofx-debuginfo",
						"version": "0.10.7",
						"release": "2.fc36",
						"arch": "i686"
					},
					{
						"name": "libofx",
						"version": "0.10.7",
						"release": "2.fc36",
						"arch": "i686"
					},
					{
						"name": "libofx-devel",
						"version": "0.10.7",
						"release": "2.fc36",
						"arch": "i686"
					},
					{
						"name": "libofx-debugsource",
						"version": "0.10.7",
						"release": "2.fc36",
						"arch": "i686"
					},
					{
						"name": "ofx",
						"version": "0.10.7",
						"release": "2.fc36",
						"arch": "i686"
					}
				],
				"ppc64le": [
					{
						"name": "libofx-debuginfo",
						"version": "0.10.7",
						"release": "2.fc36",
						"arch": "ppc64le"
					},
					{
						"name": "ofx-debuginfo",
						"version": "0.10.7",
						"release": "2.fc36",
						"arch": "ppc64le"
					},
					{
						"name": "libofx",
						"version": "0.10.7",
						"release": "2.fc36",
						"arch": "ppc64le"
					},
					{
						"name": "libofx-debugsource",
						"version": "0.10.7",
						"release": "2.fc36",
						"arch": "ppc64le"
					},
					{
						"name": "ofx",
						"version": "0.10.7",
						"release": "2.fc36",
						"arch": "ppc64le"
					},
					{
						"name": "libofx-devel",
						"version": "0.10.7",
						"release": "2.fc36",
						"arch": "ppc64le"
					}
				],
				"s390x": [
					{
						"name": "libofx-debuginfo",
						"version": "0.10.7",
						"release": "2.fc36",
						"arch": "s390x"
					},
					{
						"name": "ofx-debuginfo",
						"version": "0.10.7",
						"release": "2.fc36",
						"arch": "s390x"
					},
					{
						"name": "libofx-devel",
						"version": "0.10.7",
						"release": "2.fc36",
						"arch": "s390x"
					},
					{
						"name": "libofx",
						"version": "0.10.7",
						"release": "2.fc36",
						"arch": "s390x"
					},
					{
						"name": "libofx-debugsource",
						"version": "0.10.7",
						"release": "2.fc36",
						"arch": "s390x"
					},
					{
						"name": "ofx",
						"version": "0.10.7",
						"release": "2.fc36",
						"arch": "s390x"
					}
				],
				"src": [
					{
						"name": "libofx",
						"version": "0.10.7",
						"release": "2.fc36",
						"arch": "src"
					}
				],
				"x86_64": [
					{
						"name": "libofx-debuginfo",
						"version": "0.10.7",
						"release": "2.fc36",
						"arch": "x86_64"
					},
					{
						"name": "libofx-devel",
						"version": "0.10.7",
						"release": "2.fc36",
						"arch": "x86_64"
					},
					{
						"name": "ofx",
						"version": "0.10.7",
						"release": "2.fc36",
						"arch": "x86_64"
					},
					{
						"name": "libofx-debugsource",
						"version": "0.10.7",
						"release": "2.fc36",
						"arch": "x86_64"
					},
					{
						"name": "ofx-debuginfo",
						"version": "0.10.7",
						"release": "2.fc36",
						"arch": "x86_64"
					},
					{
						"name": "libofx",
						"version": "0.10.7",
						"release": "2.fc36",
						"arch": "x86_64"
					}
				]
			}
		}
	],
	"close_bugs": true,
	"comments": [
		{
			"id": 2722112,
			"text": "This update has been submitted for testing by limb. ",
			"timestamp": "2022-09-19 16:13:04",
			"update_id": 448751,
			"user": {
				"avatar": "https://apps.fedoraproject.org/img/icons/bodhi-24.png",
				"id": 91,
				"name": "bodhi",
				"openid": "bodhi.id.fedoraproject.org"
			},
			"user_id": 91
		},
		{
			"id": 2722113,
			"text": "This update's test gating status has been changed to 'ignored'.",
			"timestamp": "2022-09-19 16:13:04",
			"update_id": 448751,
			"user": {
				"avatar": "https://apps.fedoraproject.org/img/icons/bodhi-24.png",
				"id": 91,
				"name": "bodhi",
				"openid": "bodhi.id.fedoraproject.org"
			},
			"user_id": 91
		},
		{
			"id": 2722443,
			"text": "This update has been pushed to testing.",
			"timestamp": "2022-09-20 01:38:47",
			"update_id": 448751,
			"user": {
				"avatar": "https://apps.fedoraproject.org/img/icons/bodhi-24.png",
				"id": 91,
				"name": "bodhi",
				"openid": "bodhi.id.fedoraproject.org"
			},
			"user_id": 91
		},
		{
			"id": 2724197,
			"karma": 1,
			"timestamp": "2022-09-21 02:36:26",
			"update_id": 448751,
			"user": {
				"avatar": "https://seccdn.libravatar.org/avatar/5545678c86b7a87ee5d907a87573978f63c78b2d498edda166dac72f81003f73?s=24&d=retro",
				"email": "geraldo.simiao.kutz@gmail.com",
				"groups": [
					{
						"name": "qa"
					},
					{
						"name": "ipausers"
					},
					{
						"name": "fedora-contributor"
					},
					{
						"name": "signed_fpca"
					},
					{
						"name": "fedorabugs"
					},
					{
						"name": "ambassadors"
					},
					{
						"name": "fedora-br"
					},
					{
						"name": "advocates"
					},
					{
						"name": "respins-sig"
					}
				],
				"id": 5881,
				"name": "geraldosimiao",
				"openid": "geraldosimiao.id.fedoraproject.org"
			},
			"user_id": 5881
		},
		{
			"id": 2730672,
			"text": "This update has been submitted for stable by bodhi. ",
			"timestamp": "2022-09-27 01:38:11",
			"update_id": 448751,
			"user": {
				"avatar": "https://apps.fedoraproject.org/img/icons/bodhi-24.png",
				"id": 91,
				"name": "bodhi",
				"openid": "bodhi.id.fedoraproject.org"
			},
			"user_id": 91
		},
		{
			"id": 2731196,
			"text": "limb edited this update.",
			"timestamp": "2022-09-27 13:50:58",
			"update_id": 448751,
			"user": {
				"avatar": "https://apps.fedoraproject.org/img/icons/bodhi-24.png",
				"id": 91,
				"name": "bodhi",
				"openid": "bodhi.id.fedoraproject.org"
			},
			"user_id": 91
		},
		{
			"id": 2732051,
			"text": "This update has been pushed to stable.",
			"timestamp": "2022-09-28 12:10:51",
			"update_id": 448751,
			"user": {
				"avatar": "https://apps.fedoraproject.org/img/icons/bodhi-24.png",
				"id": 91,
				"name": "bodhi",
				"openid": "bodhi.id.fedoraproject.org"
			},
			"user_id": 91
		}
	],
	"content_type": "rpm",
	"date_modified": "2022-09-27 13:50:58",
	"date_pushed": "2022-09-28 12:10:21",
	"date_stable": "2022-09-28 12:10:21",
	"date_submitted": "2022-09-19 16:13:03",
	"date_testing": "2022-09-20 01:38:02",
	"karma": 1,
	"meets_testing_requirements": true,
	"notes": "Memory-related security fixes, BZ 2127755\n",
	"pushed": true,
	"release": {
		"branch": "f36",
		"candidate_tag": "f36-updates-candidate",
		"composed_by_bodhi": true,
		"create_automatic_updates": false,
		"dist_tag": "f36",
		"eol": "2023-05-16",
		"id_prefix": "FEDORA",
		"long_name": "Fedora 36",
		"mail_template": "fedora_errata_template",
		"name": "F36",
		"override_tag": "f36-override",
		"package_manager": "dnf",
		"pending_signing_tag": "f36-signing-pending",
		"pending_stable_tag": "f36-updates-pending",
		"pending_testing_tag": "f36-updates-testing-pending",
		"stable_tag": "f36-updates",
		"state": "archived",
		"testing_repository": "updates-testing",
		"testing_tag": "f36-updates-testing",
		"version": "36"
	},
	"require_bugs": true,
	"require_testcases": true,
	"severity": "low",
	"stable_days": 7,
	"stable_karma": 3,
	"status": "stable",
	"suggest": "unspecified",
	"test_gating_status": "ignored",
	"title": "libofx-0.10.7-2.fc36",
	"type": "security",
	"url": "https://bodhi.fedoraproject.org/updates/FEDORA-2022-95000d85e2",
	"unstable_karma": -3,
	"updateid": "FEDORA-2022-95000d85e2",
	"user": {
		"avatar": "https://seccdn.libravatar.org/avatar/7f28067f680c104a7d61fcfae961947a4f60c0e71d5ae9a714d248163c123a3d?s=24&d=retro",
		"email": "gwync@protonmail.com",
		"groups": [
			{
				"name": "releng-team"
			},
			{
				"name": "provenpackager"
			},
			{
				"name": "packager"
			},
			{
				"name": "sysadmin-devel"
			},
			{
				"name": "packaging-committee"
			},
			{
				"name": "signed_fpca"
			},
			{
				"name": "fedorabugs"
			},
			{
				"name": "sysadmin-releng"
			},
			{
				"name": "fedora-contributor"
			},
			{
				"name": "ipausers"
			},
			{
				"name": "sysadmin-cvs"
			},
			{
				"name": "cvsadmin"
			},
			{
				"name": "sysadmin"
			},
			{
				"name": "trust admins"
			},
			{
				"name": "libreoffice-sig"
			}
		],
		"id": 134,
		"name": "limb",
		"openid": "limb.id.fedoraproject.org"
	},
	"version_hash": "5eb3a53fb292202c6ca3dfe31357611cce29aabb"
}
